main.py
create_python_web_app-0.1.0.dist-info/METADATA
create_python_web_app-0.1.0.dist-info/WHEEL
create_python_web_app-0.1.0.dist-info/top_level.txt
create_python_web_app-0.1.0.dist-info/RECORD
